applauncher/__init__.py
applauncher/applauncher.py
applauncher/cli/generate/__init__.py
applauncher/cli/generate/bundle.py
applauncher/cli/generate.py
applauncher/configuration.py
applauncher/event.py
applauncher/logging.py
applauncher/service_runner.py
applauncher-2.3.0.dist-info/LICENSE
applauncher-2.3.0.dist-info/WHEEL
applauncher-2.3.0.dist-info/METADATA
applauncher-2.3.0.dist-info/RECORD
